exoplot/__init__.py
exoplot/main.py
exoplot/astrometry/__init__.py
exoplot/astrometry/astrometry_client.py
exoplot/database/__init__.py
exoplot/database/exoplanets.py
exoplot/imaging/__init__.py
exoplot/imaging/fits_imaging.py
exoplot/resources/arial.ttf
exoplot/resources/example_input_image.jpg
exoplot/resources/exoplanets.sqlite3
exoplot/services/__init__.py
exoplot/services/service_processor.py
exoplot/services/service_submit.py
exoplot-0.2.1.dist-info/LICENSE
exoplot-0.2.1.dist-info/METADATA
exoplot-0.2.1.dist-info/WHEEL
exoplot-0.2.1.dist-info/entry_points.txt
exoplot-0.2.1.dist-info/top_level.txt
exoplot-0.2.1.dist-info/RECORD
