Metadata-Version: 2.1
Name: exoplot
Version: 0.2.1
Summary: Plate solving and plotting exoplanets on your astronomy image.
Author-email: Nico Vermaas <nvermaas@xs4all.nl>
License: GNU General Public License v3.0
Project-URL: Source, https://github.com/nvermaas/exoplot
Classifier: Intended Audience :: Science/Research
Classifier: License :: OSI Approved :: Apache Software License
Classifier: Operating System :: OS Independent
Classifier: Programming Language :: Python :: 3.10
Classifier: Topic :: Scientific/Engineering
Classifier: Topic :: Scientific/Engineering :: Astronomy
Classifier: Topic :: Utilities
Requires-Python: >=3.10
License-File: LICENSE
Requires-Dist: requests
Requires-Dist: astropy
Requires-Dist: Pillow
